{"cameraMode":{"drawMode":0,"name":"Shaded","section":"Shading Mode"},"sceneLighting":true,"audioPlay":false,"sceneViewState":{"showFog":true,"showMaterialUpdate":false,"showSkybox":true,"showFlares":true,"showImageEffects":true,"showParticleSystems":true},"in2DMode":false,"pivot":{"x":4.724021911621094,"y":-16.763078689575197,"z":-6.951667785644531},"rotation":{"x":0.02004813216626644,"y":0.9796810150146484,"z":-0.15258164703845979,"w":0.12861600518226624},"size":126.39317321777344,"orthographic":false}